superlive/__init__.py
superlive/core/__init__.py
superlive/core/http_client.py
superlive/streams/__init__.py
superlive/streams/host.py
superlive_sdk-1.0.1.dist-info/LICENSE
superlive_sdk-1.0.1.dist-info/METADATA
superlive_sdk-1.0.1.dist-info/WHEEL
superlive_sdk-1.0.1.dist-info/top_level.txt
superlive_sdk-1.0.1.dist-info/RECORD
